{"upload_date": "20211003", "extractor": "youtube", "height": 1080, "like_count": 225, "duration": 1598, "fulltitle": "849\uff1a\u4e2d\u5171\u7edf\u6cbb\u672f\uff1a\u62c9\u4e00\u6d3e\uff0c\u6253\u4e00\u6d3e\uff0c\u5e2e\u4e00\u6ce2\uff0c\u6740\u4e00\u6ce2\u3002", "playlist_index": 1, "view_count": 3179, "playlist": "\u6b66\u88c5\u706d\u5171", "average_rating": 4.9130435, "_filename": "20211003_n2cUQaO012s.webm", "tags": ["\u4e2d\u7f8e\u8d38\u6613\u6218", "\u9999\u6e2f\u53cd\u9001\u4e2d", "\u4e2d\u56fd\u7ecf\u6d4e", "\u5b54\u5b50", "\u8001\u5b50", "\u5112\u5bb6\u601d\u60f3", "\u4e2d\u56fd\u6587\u5316", "\u4e2d\u56fd\u4e13\u5236", "\u7231\u56fd\u7ea2\u86c6", "\u5229\u7528\u7f8e\u56fd\u6cd5\u5f8b", "\u5077\u6e21", "\u5ddd\u666e", "\u7f8e\u56fd\u5927\u9009", "\u7279\u6717\u666e", "\u4eba\u6c11\u5e01\u8d2c\u503c", "\u65b0\u79fb\u6c11\u751f\u6d3b", "\u7f8e\u56fd\u79fb\u6c11\u751f", "\u4eba\u6c11\u5e01\u5d29\u76d8", "\u7f8e\u5143\u5347\u503c", "\u6c11\u4e3b\u4e0e\u81ea\u6cbb", "\u4e2d\u56fd\u4e92\u8054\u7f51", "\u9999\u6e2f\u8b66\u5bdf", "\u7ea2\u7c89", "\u6587\u9769\u7c89", "\u6c11\u65cf\u4e3b\u4e49\u7c89", "\u5171\u4ea7\u515a", "\u56fd\u6c11\u515a", "\u53f0\u6e7e\u6c11\u4e3b\u8fd0\u52a8", "\u4e2d\u56fd\u6c11\u4e3b\u8fd0\u52a8", "\u7f8e\u56fd\u5171\u548c\u515a", "\u7f8e\u56fd\u6c11\u4e3b\u515a", "2020\u5341\u5927\u9884\u8a00", "WTO", "\u4ea1\u56fd\u5974", "\u534e\u4e3a", "\u7f8e\u56fd\u5236\u88c1", "\u7f8e\u56fd\u5386\u53f2", "\u4e2d\u56fd\u5386\u53f2", "\u82f1\u56fd\u8131\u6b27", "\u7f8e\u56fd\u56fd\u4f1a", "\u7f8e\u56fd\u6cd5\u6848", "\u4eba\u6743\u7ec4\u7ec7", "\u601d\u60f3\u4e0e\u89e3\u653e", "\u72ec\u7acb\u601d\u8003", "\u8521\u82f1\u6587", "\u9a6c\u82f1\u4e5d", "\u4e60\u8fd1\u5e73", "\u4e2d\u56fd\u72d7\u7cae", "\u673a\u5668\u7c89", "\u5e74\u4ee3\u5411\u94b1\u770b", "\u6c6a\u7cbe\u536b", "\u56db\u5ddd\u666e\u901a\u8bdd", "\u6bdb\u6cfd\u4e1c", "\u65b0\u79fb\u6c11", "\u7f8e\u56fd\u79fb\u6c11", "\u4e2d\u56fd\u4eba\u6743", "\u65e5\u672c\u516c\u4e3b\u53f7\u90ae\u8f6e", "\u7f8e\u56fd\u5236\u88c1\u4e2d\u56fd", "\u4eba\u8138\u8bc6\u522b", "\u4e2d\u7f8e\u8131\u52fe", "\u4e2d\u56fd\u732a\u8089\u6da8\u4ef7", "\u6b66\u6c49", "\u6cd5\u6cbb\u4e0e\u4eba\u5236", "\u9999\u6e2f\u8f6e\u9677", "\u56fd\u5bb6\u5b89\u5168", "\u77e5\u8bc6\u4ea7\u6743", "\u534e\u4e3a\u76d7\u7a83", "\u7535\u89c6\u8ba4\u7f6a", "\u8001\u5d14\u8336\u9986", "\u79c0\u67285", "\u4e2d\u56fd\u7ea2\u86c6", "\u4e0a\u6d77\u5c01\u57ce", "\u4e2d\u56fd\u56fd\u6c11\u515a", "\u53f0\u6e7e\u6c11\u8fdb\u515a", "CCP", "\u534e\u4eba\u5728\u7f8e\u56fd", "\u73b0\u8c61\u5b66", "\u83cc\u6b66", "\u6b66\u88c5\u706d\u5171", "\u80a2\u89e3\u4e2d\u56fd", "\u72ec\u7acb\u5efa\u56fd"], "is_live": null, "id": "n2cUQaO012s", "dislike_count": 5, "playlist_id": "PLjNb_9N6zmdTwo8mpePEXYi2FeoXb4R_K", "abr": 129.474, "uploader_url": "http://www.youtube.com/channel/UC7AyG3ABC8DPTDSe7jWSzHA", "fps": 25, "stretched_ratio": null, "channel_url": "https://www.youtube.com/channel/UC7AyG3ABC8DPTDSe7jWSzHA", "thumbnail": "https://i.ytimg.com/vi/n2cUQaO012s/maxresdefault.jpg", "webpage_url_basename": "n2cUQaO012s", "acodec": "mp4a.40.2", "display_id": "n2cUQaO012s", "description": "#\u4e2d\u5171\u7edf\u6cbb\u672f#\u62c9\u4e00\u6d3e#\u6253\u4e00\u6d3e\n\u8fc7\u53bb\u7684\u7ecf\u5178\u300a\u5927\u4e00\u7edf\u7684\u5371\u5bb3\u300b\uff1ahttps://www.youtube.com/watch?v=vuOmD95nYTY\n\u5492\u8bed\uff1a\u53d1\u51fa\u6765\u4e0d\u770b\u5c31\u70b9\u8e29\u7684\u4eba\u5176\u59bb\u5973\u88ab\u8f6e\u5978\u540e\u5168\u5bb6\u6b7b\u7edd\u3002\u6211\u4fe1\u795e\u7684\uff0c\u5492\u8bed\u8d85\u7075\u5e94\uff01\n\u52a0\u5bc6\u90ae\u7bb1\uff1awto518@protonmail.com\n\u81ea\u6211\u4ecb\u7ecd\n\u59d3\u540d\uff1a\u770b\u5de6\u4e0a\u65b9\n\u6027\u522b\uff1a\u5f53\u7136\u4e0d\u662f\u5973\u7684\n\u751f\u65e5\uff1a365\u5929\u91cc\u7684\u9f99\u65e5\u5929\n\u5c5e\u76f8\uff1a\u975e\u5e38\u8363\u5e78\u5c5e\u51e4\u51f0\n\u5b66\u5386\u3000\uff1a\u53cd\u6b63\u4e0d\u662f\u535a\u58eb\n\u804c\u4e1a\u3000\uff1a\u5143\u5e1d\u56fd\u4e0d\u5982\u5993\u5973\n\u559c\u6b22\u6ef4\u540d\u4eba\uff1a\u8001\u5b50\uff01\n\u6700\u559c\u6b22\u6ef4\u5b57\uff1a\u62c6\n\u6700\u559c\u6b22\u6ef4\u4e8b\uff1a\u6545\u5c45\u4e0a\uff0c\u81ea\u711a\uff01\n\u4e09\u89c2\u52a0\u4e00\u89c2\n\u4eba\u751f\u89c2\uff1a\u4e00\u76f4\u4ee5\u4e3a\uff0c\u5439\u725b\u662f\u4e00\u95e8\u5f88\u6709\u524d\u9014\u7684\u804c\u4e1a\uff01\n\u4ef7\u503c\u89c2\uff1a\u559c\u6b22\u770b\u8111\u5b50\u88ab\u95e8\u5939\u7740\u7684\u4eba\uff0c\u559c\u6b22\u770b\u5634\u5df4\u6bd4\u8138\u5927\u7684\u4eba\uff01\n\u4e16\u754c\u89c2\uff1a\u8001\u5b50\u662f\u601d\u60f3\u5bb6\uff0c\u4e0d\u4fe1\u4f60\u95ee\u8001\u5b50\uff01\n\u60b2\u559c\u89c2\uff1a\u4eba\u8fd9\u4e00\u751f\u80fd\u641e\u51fa\u4e9b\u4ec0\u4e48?\u4e0d\u5916\u4e4e\u6709\u4e8c\uff1a\u7537\u4eba\u625b\u7740\u5973\u4eba\u3001\u94b1\u548c\u540d\u88ab\u4e00\u6839\u7a3b\u8349\u538b\u6b7b\uff0c\u800c\u5973\u4eba\uff0c\u5f80\u98ce\u666f\u5904\u4e00\u7ad9\uff0c\u5373\u53ef\u7b11\u50b2\u6c5f\u6e56\uff01", "format": "248 - 1920x1080 (1080p)+140 - audio only (tiny)", "playlist_uploader": "Spicy space", "uploader": "\u9ebb\u8fa3\u7a7a\u95f4", "format_id": "248+140", "uploader_id": "UC7AyG3ABC8DPTDSe7jWSzHA", "categories": ["News & Politics"], "playlist_title": "\u6b66\u88c5\u706d\u5171", "thumbnails": [{"url": "https://i.ytimg.com/vi/n2cUQaO012s/hqdefault.jpg?sqp=-oaymwEbCKgBEF5IVfKriqkDDggBFQAAiEIYAXABwAEG&rs=AOn4CLAErk2EeRwnvEEQKmyBDgmdpCnGBg", "width": 168, "resolution": "168x94", "id": "0", "height": 94}, {"url": "https://i.ytimg.com/vi/n2cUQaO012s/hqdefault.jpg?sqp=-oaymwEbCMQBEG5IVfKriqkDDggBFQAAiEIYAXABwAEG&rs=AOn4CLBhboStc9xhrUSihreKK4xHzMFv2A", "width": 196, "resolution": "196x110", "id": "1", "height": 110}, {"url": "https://i.ytimg.com/vi/n2cUQaO012s/hqdefault.jpg?sqp=-oaymwEcCPYBEIoBSFXyq4qpAw4IARUAAIhCGAFwAcABBg==&rs=AOn4CLBl8hMzvQHsegsNT7jt79tmBYb9Kw", "width": 246, "resolution": "246x138", "id": "2", "height": 138}, {"url": "https://i.ytimg.com/vi/n2cUQaO012s/hqdefault.jpg?sqp=-oaymwEcCNACELwBSFXyq4qpAw4IARUAAIhCGAFwAcABBg==&rs=AOn4CLAKDsDO_ujyXgsPM_2cMZVNkfFYbg", "width": 336, "resolution": "336x188", "id": "3", "height": 188}, {"url": "https://i.ytimg.com/vi/n2cUQaO012s/maxresdefault.jpg", "width": 1920, "resolution": "1920x1080", "id": "4", "height": 1080}], "channel_id": "UC7AyG3ABC8DPTDSe7jWSzHA", "extractor_key": "Youtube", "vcodec": "vp9", "title": "849\uff1a\u4e2d\u5171\u7edf\u6cbb\u672f\uff1a\u62c9\u4e00\u6d3e\uff0c\u6253\u4e00\u6d3e\uff0c\u5e2e\u4e00\u6ce2\uff0c\u6740\u4e00\u6ce2\u3002", "vbr": 1161.645, "ext": "webm", "channel": "Spicy space", "webpage_url": "https://www.youtube.com/watch?v=n2cUQaO012s", "formats": [{"asr": 48000, "format_note": "tiny", "protocol": "https", "format": "249 - audio only (tiny)", "tbr": 49.558, "height": null, "downloader_options": {"http_chunk_size": 10485760}, "format_id": "249", "quality": 0, "container": "webm_dash", "http_headers": {"Accept-Charset": "ISO-8859-1,utf-8;q=0.7,*;q=0.7", "Accept-Language": "en-us,en;q=0.5", "Accept-Encoding": "gzip, deflate", "Accept": "text/html,application/xhtml+xml,application/xml;q=0.9,*/*;q=0.8", "User-Agent": "Mozilla/5.0 (Windows NT 10.0; Win64; x64) AppleWebKit/537.36 (KHTML, like Gecko) Chrome/71.0.3578.126 Safari/537.36"}, "url": "https://r5---sn-vgqsrnlk.googlevideo.com/videoplayback?expire=1633506100&ei=1P5cYZC4MtbCuAK4oYPwDw&ip=69.136.135.75&id=o-AGbF8rY9m-BFisn_d809m_cOwzrnSFyFeRyPqihgem8n&itag=249&source=youtube&requiressl=yes&mh=TA&mm=31%2C29&mn=sn-vgqsrnlk%2Csn-vgqsknlr&ms=au%2Crdu&mv=m&mvi=5&pl=19&initcwndbps=1861250&vprv=1&mime=audio%2Fwebm&ns=2a4-iio1Wh71VgWKBqD5FWcG&gir=yes&clen=9900997&dur=1598.281&lmt=1633381677965279&mt=1633483974&fvip=5&keepalive=yes&fexp=24001373%2C24007246&c=WEB&txp=5431432&n=x8Iyo4jjlYluTAwA&sparams=expire%2Cei%2Cip%2Cid%2Citag%2Csource%2Crequiressl%2Cvprv%2Cmime%2Cns%2Cgir%2Cclen%2Cdur%2Clmt&sig=AOq0QJ8wRAIgQP9xyJn-2k_W0TN76qKV8TSS79vGKwdqn6RKn3scltUCIGL6Pmt_74LK0M5oSBoxcZan4KNZDDT-NHAgYm1TI8ad&lsparams=mh%2Cmm%2Cmn%2Cms%2Cmv%2Cmvi%2Cpl%2Cinitcwndbps&lsig=AG3C_xAwRAIgZBGkbB1fcF7Ai41dQ3tPicbozYAvs4Cph_0U7BZTNwACIFNN5qBnntDAUhrWtOzyHMIdoPXQgW_Re3XNK0vwyjZi", "vcodec": "none", "abr": 49.558, "width": null, "ext": "webm", "filesize": 9900997, "fps": null, "acodec": "opus"}, {"asr": 48000, "format_note": "tiny", "protocol": "https", "format": "250 - audio only (tiny)", "tbr": 56.557, "height": null, "downloader_options": {"http_chunk_size": 10485760}, "format_id": "250", "quality": 0, "container": "webm_dash", "http_headers": {"Accept-Charset": "ISO-8859-1,utf-8;q=0.7,*;q=0.7", "Accept-Language": "en-us,en;q=0.5", "Accept-Encoding": "gzip, deflate", "Accept": "text/html,application/xhtml+xml,application/xml;q=0.9,*/*;q=0.8", "User-Agent": "Mozilla/5.0 (Windows NT 10.0; Win64; x64) AppleWebKit/537.36 (KHTML, like Gecko) Chrome/71.0.3578.126 Safari/537.36"}, "url": "https://r5---sn-vgqsrnlk.googlevideo.com/videoplayback?expire=1633506100&ei=1P5cYZC4MtbCuAK4oYPwDw&ip=69.136.135.75&id=o-AGbF8rY9m-BFisn_d809m_cOwzrnSFyFeRyPqihgem8n&itag=250&source=youtube&requiressl=yes&mh=TA&mm=31%2C29&mn=sn-vgqsrnlk%2Csn-vgqsknlr&ms=au%2Crdu&mv=m&mvi=5&pl=19&initcwndbps=1861250&vprv=1&mime=audio%2Fwebm&ns=2a4-iio1Wh71VgWKBqD5FWcG&gir=yes&clen=11299264&dur=1598.281&lmt=1633381676540184&mt=1633483974&fvip=5&keepalive=yes&fexp=24001373%2C24007246&c=WEB&txp=5431432&n=x8Iyo4jjlYluTAwA&sparams=expire%2Cei%2Cip%2Cid%2Citag%2Csource%2Crequiressl%2Cvprv%2Cmime%2Cns%2Cgir%2Cclen%2Cdur%2Clmt&sig=AOq0QJ8wRAIgZMPaC9arsTPstEh0nOBm3BNXp5H0EohP2o4b196en6gCIED_01YqvaXTh50dwDlwnUukriN0Mb0w2n0S4W0hoCM0&lsparams=mh%2Cmm%2Cmn%2Cms%2Cmv%2Cmvi%2Cpl%2Cinitcwndbps&lsig=AG3C_xAwRAIgZBGkbB1fcF7Ai41dQ3tPicbozYAvs4Cph_0U7BZTNwACIFNN5qBnntDAUhrWtOzyHMIdoPXQgW_Re3XNK0vwyjZi", "vcodec": "none", "abr": 56.557, "width": null, "ext": "webm", "filesize": 11299264, "fps": null, "acodec": "opus"}, {"asr": 48000, "format_note": "tiny", "protocol": "https", "format": "251 - audio only (tiny)", "tbr": 103.543, "height": null, "downloader_options": {"http_chunk_size": 10485760}, "format_id": "251", "quality": 0, "container": "webm_dash", "http_headers": {"Accept-Charset": "ISO-8859-1,utf-8;q=0.7,*;q=0.7", "Accept-Language": "en-us,en;q=0.5", "Accept-Encoding": "gzip, deflate", "Accept": "text/html,application/xhtml+xml,application/xml;q=0.9,*/*;q=0.8", "User-Agent": "Mozilla/5.0 (Windows NT 10.0; Win64; x64) AppleWebKit/537.36 (KHTML, like Gecko) Chrome/71.0.3578.126 Safari/537.36"}, "url": "https://r5---sn-vgqsrnlk.googlevideo.com/videoplayback?expire=1633506100&ei=1P5cYZC4MtbCuAK4oYPwDw&ip=69.136.135.75&id=o-AGbF8rY9m-BFisn_d809m_cOwzrnSFyFeRyPqihgem8n&itag=251&source=youtube&requiressl=yes&mh=TA&mm=31%2C29&mn=sn-vgqsrnlk%2Csn-vgqsknlr&ms=au%2Crdu&mv=m&mvi=5&pl=19&initcwndbps=1861250&vprv=1&mime=audio%2Fwebm&ns=2a4-iio1Wh71VgWKBqD5FWcG&gir=yes&clen=20686364&dur=1598.281&lmt=1633381676456742&mt=1633483974&fvip=5&keepalive=yes&fexp=24001373%2C24007246&c=WEB&txp=5431432&n=x8Iyo4jjlYluTAwA&sparams=expire%2Cei%2Cip%2Cid%2Citag%2Csource%2Crequiressl%2Cvprv%2Cmime%2Cns%2Cgir%2Cclen%2Cdur%2Clmt&sig=AOq0QJ8wRgIhAO5mGaraiV3lgCQ6-4G1RnkcIf6izjgxkM9UlErU_h71AiEA6I04Z4JdGhqWXpPREY5tyXqbgQ29PddFBQi0lNogJik%3D&lsparams=mh%2Cmm%2Cmn%2Cms%2Cmv%2Cmvi%2Cpl%2Cinitcwndbps&lsig=AG3C_xAwRAIgZBGkbB1fcF7Ai41dQ3tPicbozYAvs4Cph_0U7BZTNwACIFNN5qBnntDAUhrWtOzyHMIdoPXQgW_Re3XNK0vwyjZi", "vcodec": "none", "abr": 103.543, "width": null, "ext": "webm", "filesize": 20686364, "fps": null, "acodec": "opus"}, {"asr": 44100, "format_note": "tiny", "protocol": "https", "format": "140 - audio only (tiny)", "tbr": 129.474, "height": null, "downloader_options": {"http_chunk_size": 10485760}, "format_id": "140", "quality": 0, "container": "m4a_dash", "http_headers": {"Accept-Charset": "ISO-8859-1,utf-8;q=0.7,*;q=0.7", "Accept-Language": "en-us,en;q=0.5", "Accept-Encoding": "gzip, deflate", "Accept": "text/html,application/xhtml+xml,application/xml;q=0.9,*/*;q=0.8", "User-Agent": "Mozilla/5.0 (Windows NT 10.0; Win64; x64) AppleWebKit/537.36 (KHTML, like Gecko) Chrome/71.0.3578.126 Safari/537.36"}, "url": "https://r5---sn-vgqsrnlk.googlevideo.com/videoplayback?expire=1633506100&ei=1P5cYZC4MtbCuAK4oYPwDw&ip=69.136.135.75&id=o-AGbF8rY9m-BFisn_d809m_cOwzrnSFyFeRyPqihgem8n&itag=140&source=youtube&requiressl=yes&mh=TA&mm=31%2C29&mn=sn-vgqsrnlk%2Csn-vgqsknlr&ms=au%2Crdu&mv=m&mvi=5&pl=19&initcwndbps=1861250&vprv=1&mime=audio%2Fmp4&ns=2a4-iio1Wh71VgWKBqD5FWcG&gir=yes&clen=25867833&dur=1598.322&lmt=1633381681243477&mt=1633483974&fvip=5&keepalive=yes&fexp=24001373%2C24007246&c=WEB&txp=5431432&n=x8Iyo4jjlYluTAwA&sparams=expire%2Cei%2Cip%2Cid%2Citag%2Csource%2Crequiressl%2Cvprv%2Cmime%2Cns%2Cgir%2Cclen%2Cdur%2Clmt&sig=AOq0QJ8wRQIgBN0rzyuko21jyuXtSRGvHIbgqKqwOZLEEHdvygsix6ICIQD1vzJeaWBmbxATrEUSyo7Rh6Rh-ae20nH29piS3SubbQ%3D%3D&lsparams=mh%2Cmm%2Cmn%2Cms%2Cmv%2Cmvi%2Cpl%2Cinitcwndbps&lsig=AG3C_xAwRAIgZBGkbB1fcF7Ai41dQ3tPicbozYAvs4Cph_0U7BZTNwACIFNN5qBnntDAUhrWtOzyHMIdoPXQgW_Re3XNK0vwyjZi", "vcodec": "none", "abr": 129.474, "width": null, "ext": "m4a", "filesize": 25867833, "fps": null, "acodec": "mp4a.40.2"}, {"asr": null, "format_note": "144p", "protocol": "https", "format": "160 - 256x144 (144p)", "tbr": 35.592, "height": 144, "downloader_options": {"http_chunk_size": 10485760}, "format_id": "160", "quality": 0, "container": "mp4_dash", "vbr": 35.592, "url": "https://r5---sn-vgqsrnlk.googlevideo.com/videoplayback?expire=1633506100&ei=1P5cYZC4MtbCuAK4oYPwDw&ip=69.136.135.75&id=o-AGbF8rY9m-BFisn_d809m_cOwzrnSFyFeRyPqihgem8n&itag=160&aitags=133%2C134%2C135%2C136%2C137%2C160%2C242%2C243%2C244%2C247%2C248%2C278&source=youtube&requiressl=yes&mh=TA&mm=31%2C29&mn=sn-vgqsrnlk%2Csn-vgqsknlr&ms=au%2Crdu&mv=m&mvi=5&pl=19&initcwndbps=1861250&vprv=1&mime=video%2Fmp4&ns=2a4-iio1Wh71VgWKBqD5FWcG&gir=yes&clen=7110352&dur=1598.160&lmt=1633384322011354&mt=1633483974&fvip=5&keepalive=yes&fexp=24001373%2C24007246&c=WEB&txp=5432432&n=x8Iyo4jjlYluTAwA&sparams=expire%2Cei%2Cip%2Cid%2Caitags%2Csource%2Crequiressl%2Cvprv%2Cmime%2Cns%2Cgir%2Cclen%2Cdur%2Clmt&sig=AOq0QJ8wRgIhAOFC0TM-kH5EV_iY7tc6VEKuVFusN0U5ATQnpDQ2Co_jAiEAvxLvxmnumVTvZKDAYhTRjSOqR-SouvFBT9ylPE2gYYw%3D&lsparams=mh%2Cmm%2Cmn%2Cms%2Cmv%2Cmvi%2Cpl%2Cinitcwndbps&lsig=AG3C_xAwRAIgZBGkbB1fcF7Ai41dQ3tPicbozYAvs4Cph_0U7BZTNwACIFNN5qBnntDAUhrWtOzyHMIdoPXQgW_Re3XNK0vwyjZi", "vcodec": "avc1.4d400c", "http_headers": {"Accept-Charset": "ISO-8859-1,utf-8;q=0.7,*;q=0.7", "Accept-Language": "en-us,en;q=0.5", "Accept-Encoding": "gzip, deflate", "Accept": "text/html,application/xhtml+xml,application/xml;q=0.9,*/*;q=0.8", "User-Agent": "Mozilla/5.0 (Windows NT 10.0; Win64; x64) AppleWebKit/537.36 (KHTML, like Gecko) Chrome/71.0.3578.126 Safari/537.36"}, "width": 256, "ext": "mp4", "filesize": 7110352, "fps": 25, "acodec": "none"}, {"asr": null, "format_note": "144p", "protocol": "https", "format": "278 - 256x144 (144p)", "tbr": 80.76, "height": 144, "downloader_options": {"http_chunk_size": 10485760}, "format_id": "278", "quality": 0, "container": "webm_dash", "vbr": 80.76, "url": "https://r5---sn-vgqsrnlk.googlevideo.com/videoplayback?expire=1633506100&ei=1P5cYZC4MtbCuAK4oYPwDw&ip=69.136.135.75&id=o-AGbF8rY9m-BFisn_d809m_cOwzrnSFyFeRyPqihgem8n&itag=278&aitags=133%2C134%2C135%2C136%2C137%2C160%2C242%2C243%2C244%2C247%2C248%2C278&source=youtube&requiressl=yes&mh=TA&mm=31%2C29&mn=sn-vgqsrnlk%2Csn-vgqsknlr&ms=au%2Crdu&mv=m&mvi=5&pl=19&initcwndbps=1861250&vprv=1&mime=video%2Fwebm&ns=2a4-iio1Wh71VgWKBqD5FWcG&gir=yes&clen=16133427&dur=1598.160&lmt=1633388287369551&mt=1633483974&fvip=5&keepalive=yes&fexp=24001373%2C24007246&c=WEB&txp=5432432&n=x8Iyo4jjlYluTAwA&sparams=expire%2Cei%2Cip%2Cid%2Caitags%2Csource%2Crequiressl%2Cvprv%2Cmime%2Cns%2Cgir%2Cclen%2Cdur%2Clmt&sig=AOq0QJ8wRQIgMUUgLqdYqulwWIe-OQ15JtWfKH5RFhKF3K-9gRkcB_0CIQDqDPZjYxFmuJ4JwLZNllNRZK5JQ7KzSir0ES41cIdQwQ%3D%3D&lsparams=mh%2Cmm%2Cmn%2Cms%2Cmv%2Cmvi%2Cpl%2Cinitcwndbps&lsig=AG3C_xAwRAIgZBGkbB1fcF7Ai41dQ3tPicbozYAvs4Cph_0U7BZTNwACIFNN5qBnntDAUhrWtOzyHMIdoPXQgW_Re3XNK0vwyjZi", "vcodec": "vp9", "http_headers": {"Accept-Charset": "ISO-8859-1,utf-8;q=0.7,*;q=0.7", "Accept-Language": "en-us,en;q=0.5", "Accept-Encoding": "gzip, deflate", "Accept": "text/html,application/xhtml+xml,application/xml;q=0.9,*/*;q=0.8", "User-Agent": "Mozilla/5.0 (Windows NT 10.0; Win64; x64) AppleWebKit/537.36 (KHTML, like Gecko) Chrome/71.0.3578.126 Safari/537.36"}, "width": 256, "ext": "webm", "filesize": 16133427, "fps": 25, "acodec": "none"}, {"asr": null, "format_note": "240p", "protocol": "https", "format": "133 - 426x240 (240p)", "tbr": 69.363, "height": 240, "downloader_options": {"http_chunk_size": 10485760}, "format_id": "133", "quality": 1, "container": "mp4_dash", "vbr": 69.363, "url": "https://r5---sn-vgqsrnlk.googlevideo.com/videoplayback?expire=1633506100&ei=1P5cYZC4MtbCuAK4oYPwDw&ip=69.136.135.75&id=o-AGbF8rY9m-BFisn_d809m_cOwzrnSFyFeRyPqihgem8n&itag=133&aitags=133%2C134%2C135%2C136%2C137%2C160%2C242%2C243%2C244%2C247%2C248%2C278&source=youtube&requiressl=yes&mh=TA&mm=31%2C29&mn=sn-vgqsrnlk%2Csn-vgqsknlr&ms=au%2Crdu&mv=m&mvi=5&pl=19&initcwndbps=1861250&vprv=1&mime=video%2Fmp4&ns=2a4-iio1Wh71VgWKBqD5FWcG&gir=yes&clen=13856779&dur=1598.160&lmt=1633384322021351&mt=1633483974&fvip=5&keepalive=yes&fexp=24001373%2C24007246&c=WEB&txp=5432432&n=x8Iyo4jjlYluTAwA&sparams=expire%2Cei%2Cip%2Cid%2Caitags%2Csource%2Crequiressl%2Cvprv%2Cmime%2Cns%2Cgir%2Cclen%2Cdur%2Clmt&sig=AOq0QJ8wRQIhALtPJ-hH0VAoT_ffCxcQJu_tAmiGebfU56wMHEOF8hC2AiBWDcIcFXxZMLjHpFuHW50T9YCD7tSxmQ4ewSNe6tCwYA%3D%3D&lsparams=mh%2Cmm%2Cmn%2Cms%2Cmv%2Cmvi%2Cpl%2Cinitcwndbps&lsig=AG3C_xAwRAIgZBGkbB1fcF7Ai41dQ3tPicbozYAvs4Cph_0U7BZTNwACIFNN5qBnntDAUhrWtOzyHMIdoPXQgW_Re3XNK0vwyjZi", "vcodec": "avc1.4d4015", "http_headers": {"Accept-Charset": "ISO-8859-1,utf-8;q=0.7,*;q=0.7", "Accept-Language": "en-us,en;q=0.5", "Accept-Encoding": "gzip, deflate", "Accept": "text/html,application/xhtml+xml,application/xml;q=0.9,*/*;q=0.8", "User-Agent": "Mozilla/5.0 (Windows NT 10.0; Win64; x64) AppleWebKit/537.36 (KHTML, like Gecko) Chrome/71.0.3578.126 Safari/537.36"}, "width": 426, "ext": "mp4", "filesize": 13856779, "fps": 25, "acodec": "none"}, {"asr": null, "format_note": "240p", "protocol": "https", "format": "242 - 426x240 (240p)", "tbr": 102.617, "height": 240, "downloader_options": {"http_chunk_size": 10485760}, "format_id": "242", "quality": 1, "container": "webm_dash", "vbr": 102.617, "url": "https://r5---sn-vgqsrnlk.googlevideo.com/videoplayback?expire=1633506100&ei=1P5cYZC4MtbCuAK4oYPwDw&ip=69.136.135.75&id=o-AGbF8rY9m-BFisn_d809m_cOwzrnSFyFeRyPqihgem8n&itag=242&aitags=133%2C134%2C135%2C136%2C137%2C160%2C242%2C243%2C244%2C247%2C248%2C278&source=youtube&requiressl=yes&mh=TA&mm=31%2C29&mn=sn-vgqsrnlk%2Csn-vgqsknlr&ms=au%2Crdu&mv=m&mvi=5&pl=19&initcwndbps=1861250&vprv=1&mime=video%2Fwebm&ns=2a4-iio1Wh71VgWKBqD5FWcG&gir=yes&clen=20499894&dur=1598.160&lmt=1633388287322978&mt=1633483974&fvip=5&keepalive=yes&fexp=24001373%2C24007246&c=WEB&txp=5432432&n=x8Iyo4jjlYluTAwA&sparams=expire%2Cei%2Cip%2Cid%2Caitags%2Csource%2Crequiressl%2Cvprv%2Cmime%2Cns%2Cgir%2Cclen%2Cdur%2Clmt&sig=AOq0QJ8wRQIhAKTL1MRexAd_NeNf2A88FGPgN_OETuqv-xsi12EJLBQOAiB6B-SGOpFDdTUmL8EE9e6ALPbEQP5TMdfeGieN6KPp7A%3D%3D&lsparams=mh%2Cmm%2Cmn%2Cms%2Cmv%2Cmvi%2Cpl%2Cinitcwndbps&lsig=AG3C_xAwRAIgZBGkbB1fcF7Ai41dQ3tPicbozYAvs4Cph_0U7BZTNwACIFNN5qBnntDAUhrWtOzyHMIdoPXQgW_Re3XNK0vwyjZi", "vcodec": "vp9", "http_headers": {"Accept-Charset": "ISO-8859-1,utf-8;q=0.7,*;q=0.7", "Accept-Language": "en-us,en;q=0.5", "Accept-Encoding": "gzip, deflate", "Accept": "text/html,application/xhtml+xml,application/xml;q=0.9,*/*;q=0.8", "User-Agent": "Mozilla/5.0 (Windows NT 10.0; Win64; x64) AppleWebKit/537.36 (KHTML, like Gecko) Chrome/71.0.3578.126 Safari/537.36"}, "width": 426, "ext": "webm", "filesize": 20499894, "fps": 25, "acodec": "none"}, {"asr": null, "format_note": "360p", "protocol": "https", "format": "134 - 640x360 (360p)", "tbr": 132.048, "height": 360, "downloader_options": {"http_chunk_size": 10485760}, "format_id": "134", "quality": 2, "container": "mp4_dash", "vbr": 132.048, "url": "https://r5---sn-vgqsrnlk.googlevideo.com/videoplayback?expire=1633506100&ei=1P5cYZC4MtbCuAK4oYPwDw&ip=69.136.135.75&id=o-AGbF8rY9m-BFisn_d809m_cOwzrnSFyFeRyPqihgem8n&itag=134&aitags=133%2C134%2C135%2C136%2C137%2C160%2C242%2C243%2C244%2C247%2C248%2C278&source=youtube&requiressl=yes&mh=TA&mm=31%2C29&mn=sn-vgqsrnlk%2Csn-vgqsknlr&ms=au%2Crdu&mv=m&mvi=5&pl=19&initcwndbps=1861250&vprv=1&mime=video%2Fmp4&ns=2a4-iio1Wh71VgWKBqD5FWcG&gir=yes&clen=26379232&dur=1598.160&lmt=1633384322027677&mt=1633483974&fvip=5&keepalive=yes&fexp=24001373%2C24007246&c=WEB&txp=5432432&n=x8Iyo4jjlYluTAwA&sparams=expire%2Cei%2Cip%2Cid%2Caitags%2Csource%2Crequiressl%2Cvprv%2Cmime%2Cns%2Cgir%2Cclen%2Cdur%2Clmt&sig=AOq0QJ8wRQIhALr442zt1CDMNhWINVF-Pyv5I9NLos-o3NP5i6sBo8NGAiACJpbGeUk6pDvEslf7jDWGryVvH-5T84eRfbd-6ouyPA%3D%3D&lsparams=mh%2Cmm%2Cmn%2Cms%2Cmv%2Cmvi%2Cpl%2Cinitcwndbps&lsig=AG3C_xAwRAIgZBGkbB1fcF7Ai41dQ3tPicbozYAvs4Cph_0U7BZTNwACIFNN5qBnntDAUhrWtOzyHMIdoPXQgW_Re3XNK0vwyjZi", "vcodec": "avc1.4d401e", "http_headers": {"Accept-Charset": "ISO-8859-1,utf-8;q=0.7,*;q=0.7", "Accept-Language": "en-us,en;q=0.5", "Accept-Encoding": "gzip, deflate", "Accept": "text/html,application/xhtml+xml,application/xml;q=0.9,*/*;q=0.8", "User-Agent": "Mozilla/5.0 (Windows NT 10.0; Win64; x64) AppleWebKit/537.36 (KHTML, like Gecko) Chrome/71.0.3578.126 Safari/537.36"}, "width": 640, "ext": "mp4", "filesize": 26379232, "fps": 25, "acodec": "none"}, {"asr": null, "format_note": "360p", "protocol": "https", "format": "243 - 640x360 (360p)", "tbr": 209.294, "height": 360, "downloader_options": {"http_chunk_size": 10485760}, "format_id": "243", "quality": 2, "container": "webm_dash", "vbr": 209.294, "url": "https://r5---sn-vgqsrnlk.googlevideo.com/videoplayback?expire=1633506100&ei=1P5cYZC4MtbCuAK4oYPwDw&ip=69.136.135.75&id=o-AGbF8rY9m-BFisn_d809m_cOwzrnSFyFeRyPqihgem8n&itag=243&aitags=133%2C134%2C135%2C136%2C137%2C160%2C242%2C243%2C244%2C247%2C248%2C278&source=youtube&requiressl=yes&mh=TA&mm=31%2C29&mn=sn-vgqsrnlk%2Csn-vgqsknlr&ms=au%2Crdu&mv=m&mvi=5&pl=19&initcwndbps=1861250&vprv=1&mime=video%2Fwebm&ns=2a4-iio1Wh71VgWKBqD5FWcG&gir=yes&clen=41810721&dur=1598.160&lmt=1633388287347045&mt=1633483974&fvip=5&keepalive=yes&fexp=24001373%2C24007246&c=WEB&txp=5432432&n=x8Iyo4jjlYluTAwA&sparams=expire%2Cei%2Cip%2Cid%2Caitags%2Csource%2Crequiressl%2Cvprv%2Cmime%2Cns%2Cgir%2Cclen%2Cdur%2Clmt&sig=AOq0QJ8wRQIhALGEgLPz1Rv4CBJCx8BW6KeDD3XgNk_4fq9Xn5jcG2n8AiAif09nnqt_-XoNcworT-DV2uBjJJAwW6s_7tv8bkW1gg%3D%3D&lsparams=mh%2Cmm%2Cmn%2Cms%2Cmv%2Cmvi%2Cpl%2Cinitcwndbps&lsig=AG3C_xAwRAIgZBGkbB1fcF7Ai41dQ3tPicbozYAvs4Cph_0U7BZTNwACIFNN5qBnntDAUhrWtOzyHMIdoPXQgW_Re3XNK0vwyjZi", "vcodec": "vp9", "http_headers": {"Accept-Charset": "ISO-8859-1,utf-8;q=0.7,*;q=0.7", "Accept-Language": "en-us,en;q=0.5", "Accept-Encoding": "gzip, deflate", "Accept": "text/html,application/xhtml+xml,application/xml;q=0.9,*/*;q=0.8", "User-Agent": "Mozilla/5.0 (Windows NT 10.0; Win64; x64) AppleWebKit/537.36 (KHTML, like Gecko) Chrome/71.0.3578.126 Safari/537.36"}, "width": 640, "ext": "webm", "filesize": 41810721, "fps": 25, "acodec": "none"}, {"asr": null, "format_note": "480p", "protocol": "https", "format": "135 - 854x480 (480p)", "tbr": 189.602, "height": 480, "downloader_options": {"http_chunk_size": 10485760}, "format_id": "135", "quality": 3, "container": "mp4_dash", "vbr": 189.602, "url": "https://r5---sn-vgqsrnlk.googlevideo.com/videoplayback?expire=1633506100&ei=1P5cYZC4MtbCuAK4oYPwDw&ip=69.136.135.75&id=o-AGbF8rY9m-BFisn_d809m_cOwzrnSFyFeRyPqihgem8n&itag=135&aitags=133%2C134%2C135%2C136%2C137%2C160%2C242%2C243%2C244%2C247%2C248%2C278&source=youtube&requiressl=yes&mh=TA&mm=31%2C29&mn=sn-vgqsrnlk%2Csn-vgqsknlr&ms=au%2Crdu&mv=m&mvi=5&pl=19&initcwndbps=1861250&vprv=1&mime=video%2Fmp4&ns=2a4-iio1Wh71VgWKBqD5FWcG&gir=yes&clen=37876897&dur=1598.160&lmt=1633384322009954&mt=1633483974&fvip=5&keepalive=yes&fexp=24001373%2C24007246&c=WEB&txp=5432432&n=x8Iyo4jjlYluTAwA&sparams=expire%2Cei%2Cip%2Cid%2Caitags%2Csource%2Crequiressl%2Cvprv%2Cmime%2Cns%2Cgir%2Cclen%2Cdur%2Clmt&sig=AOq0QJ8wRQIgRFRsVWQzkHMC0lkfmIsU92YsOabAjjsIRvOTP_XXrv8CIQCdZJHKLmmJU_EYNRAO-QEU25uGCQZrrOmay0TK9JmYjQ%3D%3D&lsparams=mh%2Cmm%2Cmn%2Cms%2Cmv%2Cmvi%2Cpl%2Cinitcwndbps&lsig=AG3C_xAwRAIgZBGkbB1fcF7Ai41dQ3tPicbozYAvs4Cph_0U7BZTNwACIFNN5qBnntDAUhrWtOzyHMIdoPXQgW_Re3XNK0vwyjZi", "vcodec": "avc1.4d401e", "http_headers": {"Accept-Charset": "ISO-8859-1,utf-8;q=0.7,*;q=0.7", "Accept-Language": "en-us,en;q=0.5", "Accept-Encoding": "gzip, deflate", "Accept": "text/html,application/xhtml+xml,application/xml;q=0.9,*/*;q=0.8", "User-Agent": "Mozilla/5.0 (Windows NT 10.0; Win64; x64) AppleWebKit/537.36 (KHTML, like Gecko) Chrome/71.0.3578.126 Safari/537.36"}, "width": 854, "ext": "mp4", "filesize": 37876897, "fps": 25, "acodec": "none"}, {"asr": null, "format_note": "480p", "protocol": "https", "format": "244 - 854x480 (480p)", "tbr": 332.608, "height": 480, "downloader_options": {"http_chunk_size": 10485760}, "format_id": "244", "quality": 3, "container": "webm_dash", "vbr": 332.608, "url": "https://r5---sn-vgqsrnlk.googlevideo.com/videoplayback?expire=1633506100&ei=1P5cYZC4MtbCuAK4oYPwDw&ip=69.136.135.75&id=o-AGbF8rY9m-BFisn_d809m_cOwzrnSFyFeRyPqihgem8n&itag=244&aitags=133%2C134%2C135%2C136%2C137%2C160%2C242%2C243%2C244%2C247%2C248%2C278&source=youtube&requiressl=yes&mh=TA&mm=31%2C29&mn=sn-vgqsrnlk%2Csn-vgqsknlr&ms=au%2Crdu&mv=m&mvi=5&pl=19&initcwndbps=1861250&vprv=1&mime=video%2Fwebm&ns=2a4-iio1Wh71VgWKBqD5FWcG&gir=yes&clen=66445220&dur=1598.160&lmt=1633388287322275&mt=1633483974&fvip=5&keepalive=yes&fexp=24001373%2C24007246&c=WEB&txp=5432432&n=x8Iyo4jjlYluTAwA&sparams=expire%2Cei%2Cip%2Cid%2Caitags%2Csource%2Crequiressl%2Cvprv%2Cmime%2Cns%2Cgir%2Cclen%2Cdur%2Clmt&sig=AOq0QJ8wRAIgQKKKxr7b41pN5nsnBXb-67H-nzNqxEJfXu1Bjqt-kggCIG4JDpWRYGz3aP0IcD4DMN365_VH3sbl3aMd6BFSQOVF&lsparams=mh%2Cmm%2Cmn%2Cms%2Cmv%2Cmvi%2Cpl%2Cinitcwndbps&lsig=AG3C_xAwRAIgZBGkbB1fcF7Ai41dQ3tPicbozYAvs4Cph_0U7BZTNwACIFNN5qBnntDAUhrWtOzyHMIdoPXQgW_Re3XNK0vwyjZi", "vcodec": "vp9", "http_headers": {"Accept-Charset": "ISO-8859-1,utf-8;q=0.7,*;q=0.7", "Accept-Language": "en-us,en;q=0.5", "Accept-Encoding": "gzip, deflate", "Accept": "text/html,application/xhtml+xml,application/xml;q=0.9,*/*;q=0.8", "User-Agent": "Mozilla/5.0 (Windows NT 10.0; Win64; x64) AppleWebKit/537.36 (KHTML, like Gecko) Chrome/71.0.3578.126 Safari/537.36"}, "width": 854, "ext": "webm", "filesize": 66445220, "fps": 25, "acodec": "none"}, {"asr": null, "format_note": "720p", "protocol": "https", "format": "136 - 1280x720 (720p)", "tbr": 278.591, "height": 720, "downloader_options": {"http_chunk_size": 10485760}, "format_id": "136", "quality": 4, "container": "mp4_dash", "vbr": 278.591, "url": "https://r5---sn-vgqsrnlk.googlevideo.com/videoplayback?expire=1633506100&ei=1P5cYZC4MtbCuAK4oYPwDw&ip=69.136.135.75&id=o-AGbF8rY9m-BFisn_d809m_cOwzrnSFyFeRyPqihgem8n&itag=136&aitags=133%2C134%2C135%2C136%2C137%2C160%2C242%2C243%2C244%2C247%2C248%2C278&source=youtube&requiressl=yes&mh=TA&mm=31%2C29&mn=sn-vgqsrnlk%2Csn-vgqsknlr&ms=au%2Crdu&mv=m&mvi=5&pl=19&initcwndbps=1861250&vprv=1&mime=video%2Fmp4&ns=2a4-iio1Wh71VgWKBqD5FWcG&gir=yes&clen=55654126&dur=1598.160&lmt=1633384322006095&mt=1633483974&fvip=5&keepalive=yes&fexp=24001373%2C24007246&c=WEB&txp=5432432&n=x8Iyo4jjlYluTAwA&sparams=expire%2Cei%2Cip%2Cid%2Caitags%2Csource%2Crequiressl%2Cvprv%2Cmime%2Cns%2Cgir%2Cclen%2Cdur%2Clmt&sig=AOq0QJ8wRAIgPiN29uenb9NMDGv8VjL5JTWzntrcvdr5woE1TCzxZ-0CIDjjRPMU6IXx_z3AMhvxftksiFSyvasA8JWUrFQVjakf&lsparams=mh%2Cmm%2Cmn%2Cms%2Cmv%2Cmvi%2Cpl%2Cinitcwndbps&lsig=AG3C_xAwRAIgZBGkbB1fcF7Ai41dQ3tPicbozYAvs4Cph_0U7BZTNwACIFNN5qBnntDAUhrWtOzyHMIdoPXQgW_Re3XNK0vwyjZi", "vcodec": "avc1.4d401f", "http_headers": {"Accept-Charset": "ISO-8859-1,utf-8;q=0.7,*;q=0.7", "Accept-Language": "en-us,en;q=0.5", "Accept-Encoding": "gzip, deflate", "Accept": "text/html,application/xhtml+xml,application/xml;q=0.9,*/*;q=0.8", "User-Agent": "Mozilla/5.0 (Windows NT 10.0; Win64; x64) AppleWebKit/537.36 (KHTML, like Gecko) Chrome/71.0.3578.126 Safari/537.36"}, "width": 1280, "ext": "mp4", "filesize": 55654126, "fps": 25, "acodec": "none"}, {"asr": null, "format_note": "720p", "protocol": "https", "format": "247 - 1280x720 (720p)", "tbr": 623.764, "height": 720, "downloader_options": {"http_chunk_size": 10485760}, "format_id": "247", "quality": 4, "container": "webm_dash", "vbr": 623.764, "url": "https://r5---sn-vgqsrnlk.googlevideo.com/videoplayback?expire=1633506100&ei=1P5cYZC4MtbCuAK4oYPwDw&ip=69.136.135.75&id=o-AGbF8rY9m-BFisn_d809m_cOwzrnSFyFeRyPqihgem8n&itag=247&aitags=133%2C134%2C135%2C136%2C137%2C160%2C242%2C243%2C244%2C247%2C248%2C278&source=youtube&requiressl=yes&mh=TA&mm=31%2C29&mn=sn-vgqsrnlk%2Csn-vgqsknlr&ms=au%2Crdu&mv=m&mvi=5&pl=19&initcwndbps=1861250&vprv=1&mime=video%2Fwebm&ns=2a4-iio1Wh71VgWKBqD5FWcG&gir=yes&clen=124609506&dur=1598.160&lmt=1633388287754671&mt=1633483974&fvip=5&keepalive=yes&fexp=24001373%2C24007246&c=WEB&txp=5432432&n=x8Iyo4jjlYluTAwA&sparams=expire%2Cei%2Cip%2Cid%2Caitags%2Csource%2Crequiressl%2Cvprv%2Cmime%2Cns%2Cgir%2Cclen%2Cdur%2Clmt&sig=AOq0QJ8wRQIhAI3KUPMDbyyFWkWvAFek8oO4WNpm5KmJSbK-xTNqOjC2AiBjdG49ycuM5jIXvoilzafgrs-dn6WBzv3pstFZqtqB0Q%3D%3D&lsparams=mh%2Cmm%2Cmn%2Cms%2Cmv%2Cmvi%2Cpl%2Cinitcwndbps&lsig=AG3C_xAwRAIgZBGkbB1fcF7Ai41dQ3tPicbozYAvs4Cph_0U7BZTNwACIFNN5qBnntDAUhrWtOzyHMIdoPXQgW_Re3XNK0vwyjZi", "vcodec": "vp9", "http_headers": {"Accept-Charset": "ISO-8859-1,utf-8;q=0.7,*;q=0.7", "Accept-Language": "en-us,en;q=0.5", "Accept-Encoding": "gzip, deflate", "Accept": "text/html,application/xhtml+xml,application/xml;q=0.9,*/*;q=0.8", "User-Agent": "Mozilla/5.0 (Windows NT 10.0; Win64; x64) AppleWebKit/537.36 (KHTML, like Gecko) Chrome/71.0.3578.126 Safari/537.36"}, "width": 1280, "ext": "webm", "filesize": 124609506, "fps": 25, "acodec": "none"}, {"asr": null, "format_note": "1080p", "protocol": "https", "format": "137 - 1920x1080 (1080p)", "tbr": 1082.874, "height": 1080, "downloader_options": {"http_chunk_size": 10485760}, "format_id": "137", "quality": 5, "container": "mp4_dash", "vbr": 1082.874, "url": "https://r5---sn-vgqsrnlk.googlevideo.com/videoplayback?expire=1633506100&ei=1P5cYZC4MtbCuAK4oYPwDw&ip=69.136.135.75&id=o-AGbF8rY9m-BFisn_d809m_cOwzrnSFyFeRyPqihgem8n&itag=137&aitags=133%2C134%2C135%2C136%2C137%2C160%2C242%2C243%2C244%2C247%2C248%2C278&source=youtube&requiressl=yes&mh=TA&mm=31%2C29&mn=sn-vgqsrnlk%2Csn-vgqsknlr&ms=au%2Crdu&mv=m&mvi=5&pl=19&initcwndbps=1861250&vprv=1&mime=video%2Fmp4&ns=2a4-iio1Wh71VgWKBqD5FWcG&gir=yes&clen=216325874&dur=1598.160&lmt=1633383050928184&mt=1633483974&fvip=5&keepalive=yes&fexp=24001373%2C24007246&c=WEB&txp=5432432&n=x8Iyo4jjlYluTAwA&sparams=expire%2Cei%2Cip%2Cid%2Caitags%2Csource%2Crequiressl%2Cvprv%2Cmime%2Cns%2Cgir%2Cclen%2Cdur%2Clmt&sig=AOq0QJ8wRQIhAKQwNzXY-lOVyCvwj2hziQjLMbct87kc0c-AOuwIh6s3AiB6GQnIb96GIu6hDeCVvPqgn-zmAQn26CrZq9zhaKif4w%3D%3D&lsparams=mh%2Cmm%2Cmn%2Cms%2Cmv%2Cmvi%2Cpl%2Cinitcwndbps&lsig=AG3C_xAwRAIgZBGkbB1fcF7Ai41dQ3tPicbozYAvs4Cph_0U7BZTNwACIFNN5qBnntDAUhrWtOzyHMIdoPXQgW_Re3XNK0vwyjZi", "vcodec": "avc1.640028", "http_headers": {"Accept-Charset": "ISO-8859-1,utf-8;q=0.7,*;q=0.7", "Accept-Language": "en-us,en;q=0.5", "Accept-Encoding": "gzip, deflate", "Accept": "text/html,application/xhtml+xml,application/xml;q=0.9,*/*;q=0.8", "User-Agent": "Mozilla/5.0 (Windows NT 10.0; Win64; x64) AppleWebKit/537.36 (KHTML, like Gecko) Chrome/71.0.3578.126 Safari/537.36"}, "width": 1920, "ext": "mp4", "filesize": 216325874, "fps": 25, "acodec": "none"}, {"asr": null, "format_note": "1080p", "protocol": "https", "format": "248 - 1920x1080 (1080p)", "tbr": 1161.645, "height": 1080, "downloader_options": {"http_chunk_size": 10485760}, "format_id": "248", "quality": 5, "container": "webm_dash", "vbr": 1161.645, "url": "https://r5---sn-vgqsrnlk.googlevideo.com/videoplayback?expire=1633506100&ei=1P5cYZC4MtbCuAK4oYPwDw&ip=69.136.135.75&id=o-AGbF8rY9m-BFisn_d809m_cOwzrnSFyFeRyPqihgem8n&itag=248&aitags=133%2C134%2C135%2C136%2C137%2C160%2C242%2C243%2C244%2C247%2C248%2C278&source=youtube&requiressl=yes&mh=TA&mm=31%2C29&mn=sn-vgqsrnlk%2Csn-vgqsknlr&ms=au%2Crdu&mv=m&mvi=5&pl=19&initcwndbps=1861250&vprv=1&mime=video%2Fwebm&ns=2a4-iio1Wh71VgWKBqD5FWcG&gir=yes&clen=232061826&dur=1598.160&lmt=1633382772168391&mt=1633483974&fvip=5&keepalive=yes&fexp=24001373%2C24007246&c=WEB&txp=5432432&n=x8Iyo4jjlYluTAwA&sparams=expire%2Cei%2Cip%2Cid%2Caitags%2Csource%2Crequiressl%2Cvprv%2Cmime%2Cns%2Cgir%2Cclen%2Cdur%2Clmt&sig=AOq0QJ8wRQIgHXc3tP0NhgFNWTMWvTfQ9xdKSwUungtlhx80sg_S8hMCIQDI4KlXSj9HA9SDutAyXEFXMt8nvfXPC0sTmBOZ5Nc6Lg%3D%3D&lsparams=mh%2Cmm%2Cmn%2Cms%2Cmv%2Cmvi%2Cpl%2Cinitcwndbps&lsig=AG3C_xAwRAIgZBGkbB1fcF7Ai41dQ3tPicbozYAvs4Cph_0U7BZTNwACIFNN5qBnntDAUhrWtOzyHMIdoPXQgW_Re3XNK0vwyjZi", "vcodec": "vp9", "http_headers": {"Accept-Charset": "ISO-8859-1,utf-8;q=0.7,*;q=0.7", "Accept-Language": "en-us,en;q=0.5", "Accept-Encoding": "gzip, deflate", "Accept": "text/html,application/xhtml+xml,application/xml;q=0.9,*/*;q=0.8", "User-Agent": "Mozilla/5.0 (Windows NT 10.0; Win64; x64) AppleWebKit/537.36 (KHTML, like Gecko) Chrome/71.0.3578.126 Safari/537.36"}, "width": 1920, "ext": "webm", "filesize": 232061826, "fps": 25, "acodec": "none"}, {"asr": 44100, "format_note": "360p", "protocol": "https", "format": "18 - 640x360 (360p)", "tbr": 381.303, "height": 360, "format_id": "18", "quality": 2, "http_headers": {"Accept-Charset": "ISO-8859-1,utf-8;q=0.7,*;q=0.7", "Accept-Language": "en-us,en;q=0.5", "Accept-Encoding": "gzip, deflate", "Accept": "text/html,application/xhtml+xml,application/xml;q=0.9,*/*;q=0.8", "User-Agent": "Mozilla/5.0 (Windows NT 10.0; Win64; x64) AppleWebKit/537.36 (KHTML, like Gecko) Chrome/71.0.3578.126 Safari/537.36"}, "url": "https://r5---sn-vgqsrnlk.googlevideo.com/videoplayback?expire=1633506100&ei=1P5cYZC4MtbCuAK4oYPwDw&ip=69.136.135.75&id=o-AGbF8rY9m-BFisn_d809m_cOwzrnSFyFeRyPqihgem8n&itag=18&source=youtube&requiressl=yes&mh=TA&mm=31%2C29&mn=sn-vgqsrnlk%2Csn-vgqsknlr&ms=au%2Crdu&mv=m&mvi=5&pl=19&initcwndbps=1861250&vprv=1&mime=video%2Fmp4&ns=hmDNlIwMbdJvSsfCAujGBfEG&gir=yes&clen=76180634&ratebypass=yes&dur=1598.322&lmt=1633341476622714&mt=1633483974&fvip=5&fexp=24001373%2C24007246&c=WEB&txp=5430434&n=56tFnlGWpYVgJIKx&sparams=expire%2Cei%2Cip%2Cid%2Citag%2Csource%2Crequiressl%2Cvprv%2Cmime%2Cns%2Cgir%2Cclen%2Cratebypass%2Cdur%2Clmt&sig=AOq0QJ8wRQIhAO28N9d3vZ-L-LJRHRXdjxydMdpXfxQ6sWIYdJq7PbmjAiBHkOGJvUkIoDKnFM2U5QajHysnOQZW54UmZg36QBoadg%3D%3D&lsparams=mh%2Cmm%2Cmn%2Cms%2Cmv%2Cmvi%2Cpl%2Cinitcwndbps&lsig=AG3C_xAwRAIgZBGkbB1fcF7Ai41dQ3tPicbozYAvs4Cph_0U7BZTNwACIFNN5qBnntDAUhrWtOzyHMIdoPXQgW_Re3XNK0vwyjZi", "vcodec": "avc1.42001E", "width": 640, "ext": "mp4", "filesize": 76180634, "fps": 25, "acodec": "mp4a.40.2"}, {"asr": 44100, "format_note": "720p", "protocol": "https", "format": "22 - 1280x720 (720p)", "tbr": 407.717, "height": 720, "format_id": "22", "quality": 4, "http_headers": {"Accept-Charset": "ISO-8859-1,utf-8;q=0.7,*;q=0.7", "Accept-Language": "en-us,en;q=0.5", "Accept-Encoding": "gzip, deflate", "Accept": "text/html,application/xhtml+xml,application/xml;q=0.9,*/*;q=0.8", "User-Agent": "Mozilla/5.0 (Windows NT 10.0; Win64; x64) AppleWebKit/537.36 (KHTML, like Gecko) Chrome/71.0.3578.126 Safari/537.36"}, "url": "https://r5---sn-vgqsrnlk.googlevideo.com/videoplayback?expire=1633506100&ei=1P5cYZC4MtbCuAK4oYPwDw&ip=69.136.135.75&id=o-AGbF8rY9m-BFisn_d809m_cOwzrnSFyFeRyPqihgem8n&itag=22&source=youtube&requiressl=yes&mh=TA&mm=31%2C29&mn=sn-vgqsrnlk%2Csn-vgqsknlr&ms=au%2Crdu&mv=m&mvi=5&pl=19&initcwndbps=1861250&vprv=1&mime=video%2Fmp4&ns=hmDNlIwMbdJvSsfCAujGBfEG&cnr=14&ratebypass=yes&dur=1598.322&lmt=1633384395599746&mt=1633483974&fvip=5&fexp=24001373%2C24007246&c=WEB&txp=5432432&n=56tFnlGWpYVgJIKx&sparams=expire%2Cei%2Cip%2Cid%2Citag%2Csource%2Crequiressl%2Cvprv%2Cmime%2Cns%2Ccnr%2Cratebypass%2Cdur%2Clmt&sig=AOq0QJ8wRQIgBqMyQFdFfU4D6HpXQD80KaprVqoXvxpVs5gdDfvuMOACIQDfyROTqiejnhY117FrWkORdID9XJaAZsywAqdinl1p9Q%3D%3D&lsparams=mh%2Cmm%2Cmn%2Cms%2Cmv%2Cmvi%2Cpl%2Cinitcwndbps&lsig=AG3C_xAwRAIgZBGkbB1fcF7Ai41dQ3tPicbozYAvs4Cph_0U7BZTNwACIFNN5qBnntDAUhrWtOzyHMIdoPXQgW_Re3XNK0vwyjZi", "vcodec": "avc1.64001F", "width": 1280, "ext": "mp4", "filesize": null, "fps": 25, "acodec": "mp4a.40.2"}], "playlist_uploader_id": "UC7AyG3ABC8DPTDSe7jWSzHA", "resolution": null, "width": 1920, "n_entries": 201, "age_limit": 0}